firelib
